dj_payment/__init__.py
dj_payment/admin.py
dj_payment/apps.py
dj_payment/handlers.py
dj_payment/models.py
dj_payment/serializers.py
dj_payment/services.py
dj_payment/signals.py
dj_payment/tests.py
dj_payment/urls.py
dj_payment/views.py
starco_dj_payment-1.0.0.dist-info/METADATA
starco_dj_payment-1.0.0.dist-info/WHEEL
starco_dj_payment-1.0.0.dist-info/top_level.txt
starco_dj_payment-1.0.0.dist-info/RECORD
