Metadata-Version: 2.4
Name: starco-dj-payment
Version: 1.0.0
Summary: A Django pluggable app for payments.
Author: Mojtaba
Author-email: m.tahmasbi0111@yahoo.com
License: MIT
Classifier: Framework :: Django
Classifier: Programming Language :: Python :: 3
Requires-Dist: Django>=4.0
Requires-Dist: starco-dj-utils
Requires-Dist: requests
Requires-Dist: starco-utility==1.3.4
Dynamic: author
Dynamic: author-email
Dynamic: classifier
Dynamic: license
Dynamic: requires-dist
Dynamic: summary
